MANIFEST.in
setup.py
uberdoc/__init__.py
uberdoc/config.py
uberdoc/default_gitignore
uberdoc/termcolor.py
uberdoc/uberdoc.cfg
uberdoc/udoc.py
uberdoc.egg-info/PKG-INFO
uberdoc.egg-info/SOURCES.txt
uberdoc.egg-info/dependency_links.txt
uberdoc.egg-info/entry_points.txt
uberdoc.egg-info/requires.txt
uberdoc.egg-info/top_level.txt
uberdoc/sample/.DS_Store
uberdoc/sample/toc.txt
uberdoc/sample/chapter1/.DS_Store
uberdoc/sample/chapter1/chapter1.md
uberdoc/sample/chapter1/img/.DS_Store
uberdoc/sample/chapter1/img/star.pdf
uberdoc/sample/chapter1/img/star.png
uberdoc/sample/chapter2/chapter2.md
uberdoc/sample/templating/some.md
uberdoc/sample/templating/templating.md
uberdoc/style/default.css
uberdoc/style/default.js
uberdoc/style/jqtree-circle.png
uberdoc/style/jqtree.css
uberdoc/style/jquery-1.10.2.min.js
uberdoc/style/tree.jquery.js
uberdoc/templates/.DS_Store
uberdoc/templates/default.html
uberdoc/templates/default.tex